ftscursor/__init__.py
ftscursor/example_script.py
ftscursor/ftscursor.py
ftscursor-0.5.8.dist-info/LICENSE
ftscursor-0.5.8.dist-info/METADATA
ftscursor-0.5.8.dist-info/WHEEL
ftscursor-0.5.8.dist-info/entry_points.txt
ftscursor-0.5.8.dist-info/top_level.txt
ftscursor-0.5.8.dist-info/RECORD
