Metadata-Version: 2.1
Name: ftscursor
Version: 0.5.8
Summary: A sqlite3 cursor with extra methods to support FTS3/4/5
Home-page: https://gitlab.com/aaylward/ftscursor
Author: Anthony Aylward
Author-email: aaylward@salk.edu
License: UNKNOWN
Platform: UNKNOWN
Classifier: Programming Language :: Python :: 3
Classifier: License :: OSI Approved :: MIT License
Classifier: Operating System :: OS Independent
License-File: LICENSE
